{"cameraMode":{"drawMode":0,"name":"Shaded","section":"Shading Mode"},"sceneLighting":true,"audioPlay":false,"sceneViewState":{"m_AlwaysRefresh":false,"showFog":true,"showSkybox":true,"showFlares":true,"showImageEffects":true,"showParticleSystems":true,"showVisualEffectGraphs":true,"m_FxEnabled":true},"in2DMode":false,"pivot":{"x":4.114189624786377,"y":2.202427864074707,"z":1.4139957427978516},"rotation":{"x":-0.08239930868148804,"y":0.013442962430417538,"z":-0.00111159379594028,"w":-0.9965112209320068},"size":8.5374174118042,"orthographic":false}